{
  "exam": "ossc",
  "name": "OSSC RI/Amin",
  "date": "2026-06-15",
  "questionCount": 30,
  "questions": [
    {
      "id": 1,
      "category": "Odisha General Knowledge",
      "question": "Which is the largest river flowing through Odisha?",
      "options": [
        "Godavari",
        "Mahanadi",
        "Krishna",
        "Brahmani"
      ],
      "correct": 1,
      "explanation": "The Mahanadi is the largest river flowing through Odisha, originating from Chhattisgarh and flowing into the Bay of Bengal."
    },
    {
      "id": 2,
      "category": "Odisha General Knowledge",
      "question": "Which tribal community is primarily found in the Kandhamal district of Odisha?",
      "options": [
        "Santal",
        "Konds",
        "Gonds",
        "Oraons"
      ],
      "correct": 1,
      "explanation": "The Konds are prominently found in Kandhamal district and are known for their distinct culture and traditions."
    },
    {
      "id": 3,
      "category": "Odisha General Knowledge",
      "question": "Which lake in Odisha is famous for its migratory birds and is located near Baripada?",
      "options": [
        "Chilika Lake",
        "Bhitarkanika Lake",
        "Kanjia Lake",
        "Debadatta Lake"
      ],
      "correct": 2,
      "explanation": "Kanjia Lake, near Baripada, is known for its rich biodiversity and migratory birds, especially during winter."
    },
    {
      "id": 4,
      "category": "Odisha General Knowledge",
      "question": "Which festival is celebrated to mark the Rath Yatra in Odisha?",
      "options": [
        "Diwali",
        "Durga Puja",
        "Rath Yatra",
        "Holi"
      ],
      "correct": 2,
      "explanation": "The Rath Yatra is a famous festival in Odisha, especially in Puri, celebrating Lord Jagannath's chariot procession."
    },
    {
      "id": 5,
      "category": "Odisha General Knowledge",
      "question": "Who among the following was a renowned Odia poet and philosopher?",
      "options": [
        "Kabi Samrat Upendra Bhanja",
        "Rabindranath Tagore",
        "Bankim Chandra Chattopadhyay",
        "Ram Kumar Ray"
      ],
      "correct": 0,
      "explanation": "Kabi Samrat Upendra Bhanja was a celebrated Odia poet and philosopher from Odisha."
    },
    {
      "id": 6,
      "category": "Odisha General Knowledge",
      "question": "Which fort in Odisha is famous for its archaeological importance and is located in Bhubaneswar?",
      "options": [
        "Udayagiri Fort",
        "Barabati Fort",
        "Rajarani Fort",
        "Khandagiri Caves"
      ],
      "correct": 3,
      "explanation": "The Khandagiri Caves are renowned archaeological sites in Bhubaneswar, with historical significance dating back to Jain monks."
    },
    {
      "id": 7,
      "category": "Indian History & Culture",
      "question": "Which ancient Indian university was situated in Odisha?",
      "options": [
        "Takshashila",
        "Nalanda",
        "Ujjain",
        "Kalinga University (Ancient)"
      ],
      "correct": 3,
      "explanation": "Kalinga University (Ancient) in Odisha was an important center of education in ancient India."
    },
    {
      "id": 8,
      "category": "Indian History & Culture",
      "question": "Who was the leader of the Revolt of 1857 from Odisha?",
      "options": [
        "Utkal Gourav Madhusudhan Das",
        "Baji Rout",
        "Jagabandhu Bidyadhar",
        "Utkal Gourav Madhusudhan Das"
      ],
      "correct": 2,
      "explanation": "Jagabandhu Bidyadhar led the Paika Rebellion in Odisha during the 1857 revolt against British rule."
    },
    {
      "id": 9,
      "category": "Indian History & Culture",
      "question": "Which heritage site in Odisha is a UNESCO World Heritage Site?",
      "options": [
        "Konark Sun Temple",
        "Lingaraj Temple",
        "Jagannath Temple",
        "Udayagiri Caves"
      ],
      "correct": 0,
      "explanation": "The Konark Sun Temple is a UNESCO World Heritage Site known for its architectural grandeur."
    },
    {
      "id": 10,
      "category": "Indian History & Culture",
      "question": "Which movement was associated with Mahatma Gandhi?",
      "options": [
        "Non-Cooperation Movement",
        "Swadeshi Movement",
        "Champaran Satyagraha",
        "All of the above"
      ],
      "correct": 3,
      "explanation": "All listed movements were part of Mahatma Gandhi’s efforts during India’s struggle for independence."
    },
    {
      "id": 11,
      "category": "Geography",
      "question": "Which is the highest mountain peak in India?",
      "options": [
        "Kangchenjunga",
        "Mount Everest",
        "Nanda Devi",
        "Dhaulagiri"
      ],
      "correct": 1,
      "explanation": "Mount Everest, located in the Himalayas, is the highest peak in India and the world."
    },
    {
      "id": 12,
      "category": "Geography",
      "question": "Odisha has an industry-rich soil type known as?",
      "options": [
        "Alluvial Soil",
        "Black Soil",
        "Laterite Soil",
        "Desert Soil"
      ],
      "correct": 2,
      "explanation": "Odisha predominantly has Laterite soil, suitable for certain crops and mineral deposits."
    },
    {
      "id": 13,
      "category": "Geography",
      "question": "Which mineral is most abundantly found in Odisha?",
      "options": [
        "Coal",
        "Bauxite",
        "Chromite",
        "Iron Ore"
      ],
      "correct": 4,
      "explanation": "Odisha is rich in Iron Ore deposits, making it a leading producer in India."
    },
    {
      "id": 14,
      "category": "Geography",
      "question": "Which climate zone does Odisha primarily fall under?",
      "options": [
        "Tropical monsoon",
        "Desert",
        "Temperate",
        "Tundra"
      ],
      "correct": 0,
      "explanation": "Odisha experiences a Tropical monsoon climate with heavy seasonal rainfall."
    },
    {
      "id": 15,
      "category": "Indian Polity & Constitution",
      "question": "Which article of the Indian Constitution guarantees Fundamental Rights?",
      "options": [
        "Article 14",
        "Article 19",
        "Article 21",
        "All of the above"
      ],
      "correct": 3,
      "explanation": "Articles 14, 19, 21 and others collectively guarantee Fundamental Rights under the Constitution."
    },
    {
      "id": 16,
      "category": "Indian Polity & Constitution",
      "question": "Who is the current President of India?",
      "options": [
        "Droupadi Murmu",
        "Ram Nath Kovind",
        "Pranab Mukherjee",
        "A.P.J. Abdul Kalam"
      ],
      "correct": 0,
      "explanation": "Droupadi Murmu is the current President of India since 25 July 2022."
    },
    {
      "id": 17,
      "category": "Indian Polity & Constitution",
      "question": "Which part of the Indian Constitution deals with the Directive Principles of State Policy?",
      "options": [
        "Part III",
        "Part IV",
        "Part V",
        "Part VI"
      ],
      "correct": 1,
      "explanation": "Part IV of the Indian Constitution deals with Directive Principles of State Policy."
    },
    {
      "id": 18,
      "category": "Indian Polity & Constitution",
      "question": "How many members are there in the Lok Sabha?",
      "options": [
        "545",
        "545 plus nominated members",
        "552",
        "530"
      ],
      "correct": 1,
      "explanation": "The Lok Sabha has 545 elected members plus some nominated members, totaling 545+."
    },
    {
      "id": 19,
      "category": "General Science",
      "question": "What is the basic unit of life in biology?",
      "options": [
        "Atom",
        "Cell",
        "Molecule",
        "Tissue"
      ],
      "correct": 1,
      "explanation": "The cell is the basic structural and functional unit of all living organisms."
    },
    {
      "id": 20,
      "category": "General Science",
      "question": "Which gas is most responsible for the greenhouse effect?",
      "options": [
        "Oxygen",
        "Carbon dioxide",
        "Nitrogen",
        "Argon"
      ],
      "correct": 1,
      "explanation": "Carbon dioxide is the primary greenhouse gas responsible for global warming."
    },
    {
      "id": 21,
      "category": "General Science",
      "question": "Which vitamin is mainly produced when the skin is exposed to sunlight?",
      "options": [
        "Vitamin A",
        "Vitamin B",
        "Vitamin C",
        "Vitamin D"
      ],
      "correct": 3,
      "explanation": "Vitamin D is synthesized in the skin upon exposure to sunlight."
    },
    {
      "id": 22,
      "category": "General Science",
      "question": "Which disease is caused by deficiency of Vitamin C?",
      "options": [
        "Rickets",
        "Scurvy",
        "Anemia",
        "Night blindness"
      ],
      "correct": 1,
      "explanation": "Vitamin C deficiency causes Scurvy, characterized by weakness and bleeding gums."
    },
    {
      "id": 23,
      "category": "Mental Ability & Reasoning",
      "question": "What comes next in the series: 2, 4, 8, 16, ?",
      "options": [
        "32",
        "24",
        "30",
        "28"
      ],
      "correct": 0,
      "explanation": "The series doubles each time; next is 32."
    },
    {
      "id": 24,
      "category": "Mental Ability & Reasoning",
      "question": "If in a certain code, 'ODISHA' is written as 'PJEITB', what is the code for 'RAJ?'",
      "options": [
        "QBL",
        "QCK",
        "QAL",
        "QDM"
      ],
      "correct": 2,
      "explanation": "The pattern involves shifting letters; 'R' to 'Q' (-1), 'A' to 'B' (+1), 'J' to 'L' (+2). Applying similar logic yields 'QAL'."
    },
    {
      "id": 25,
      "category": "Mental Ability & Reasoning",
      "question": "If 'Mother' is coded as 'Npqstg', what is the code for 'Father'?",
      "options": [
        "Gbtg",
        "Gvsg",
        "Gthu",
        "Gstg"
      ],
      "correct": 1,
      "explanation": "Pattern involves shifting each letter; 'F' (+1) gives 'G,' 'a' (+1) gives 'v', etc., resulting in 'Gvsg'."
    },
    {
      "id": 26,
      "category": "Current Affairs",
      "question": "Who is the current Chief Minister of Odisha?",
      "options": [
        "Naveen Patnaik",
        "Mohan Charan Majhi",
        "Nirmala Sitharaman",
        "Biplab Kumar Deb"
      ],
      "correct": 1,
      "explanation": "Mohan Charan Majhi has been the Chief Minister of Odisha since 12 June 2024."
    },
    {
      "id": 27,
      "category": "Current Affairs",
      "question": "Which scheme was launched by the Government of India for financial inclusion in rural areas?",
      "options": [
        "Pradhan Mantri Jan Dhan Yojana",
        "Swachh Bharat Abhiyan",
        "Make in India",
        "Digital India"
      ],
      "correct": 0,
      "explanation": "Pradhan Mantri Jan Dhan Yojana aims at increasing financial inclusion by opening bank accounts for the unbanked."
    },
    {
      "id": 28,
      "category": "Current Affairs",
      "question": "Who won the prestigious Arjuna Award in 2025?",
      "options": [
        "Neeraj Chopra",
        "PV Sindhu",
        "Mary Kom",
        "Rohit Sharma"
      ],
      "correct": 0,
      "explanation": "Neeraj Chopra, the Olympic medalist, was awarded the Arjuna Award in 2025 for his excellence in athletics."
    },
    {
      "id": 29,
      "category": "Current Affairs",
      "question": "Which recent event was held in Odisha in 2025 to promote tourism?",
      "options": [
        "Odisha State Tourism Campaign",
        "Odisha International Sports Meet",
        "Odisha Cultural Fest",
        "Odisha Wildlife Festival"
      ],
      "correct": 2,
      "explanation": "The Odisha Cultural Fest was organized in 2025 to showcase Odisha's rich cultural heritage and promote tourism."
    },
    {
      "id": 30,
      "category": "Current Affairs",
      "question": "Which Indian athlete qualified for the 2024 Paris Olympics from Odisha?",
      "options": [
        "Dutee Chand",
        "Pravasi Das",
        "Sudarshan Patnaik",
        "Anju Devi"
      ],
      "correct": 0,
      "explanation": "Dutee Chand, an acclaimed sprinter from Odisha, qualified for the 2024 Paris Olympics."
    }
  ]
}