{
  "exam": "ssb",
  "name": "SSB",
  "date": "2026-03-21",
  "questionCount": 60,
  "questions": [
    {
      "id": 1,
      "category": "General Awareness & GK",
      "question": "Who is the author of the book 'India After Gandhi'?",
      "options": [
        "Ramachandra Guha",
        "Narendra Modi",
        "Amit Shah",
        "Arvind Kejriwal"
      ],
      "correct": 0,
      "explanation": "The book 'India After Gandhi' is written by Ramachandra Guha, an Indian historian and writer. The book is a comprehensive history of India from 1947 to 2007 and provides an in-depth analysis of the country's social, economic, and political developments."
    },
    {
      "id": 2,
      "category": "General Awareness & GK",
      "question": "What is the name of the national animal of India?",
      "options": [
        "Lion",
        "Tiger",
        "Elephant",
        "Peacock"
      ],
      "correct": 1,
      "explanation": "The tiger is the national animal of India. It is a majestic and powerful animal that is native to the country and is an important part of Indian culture and heritage."
    },
    {
      "id": 3,
      "category": "General Awareness & GK",
      "question": "Who was the first President of India?",
      "options": [
        "Dr. Rajendra Prasad",
        "Jawaharlal Nehru",
        "Sardar Patel",
        "Subhas Chandra Bose"
      ],
      "correct": 0,
      "explanation": "Dr. Rajendra Prasad was the first President of India, serving from 1950 to 1962. He was a prominent leader in the Indian independence movement and played a key role in the country's transition to independence."
    },
    {
      "id": 4,
      "category": "General Awareness & GK",
      "question": "What is the name of the highest award given to civilians in India?",
      "options": [
        "Bharat Ratna",
        "Padma Vibhushan",
        "Padma Bhushan",
        "Padma Shri"
      ],
      "correct": 0,
      "explanation": "The Bharat Ratna is the highest award given to civilians in India. It is awarded to individuals who have made exceptional contributions to the country in fields such as art, literature, science, and public service."
    },
    {
      "id": 5,
      "category": "General Awareness & GK",
      "question": "Which Indian state has the highest number of national parks?",
      "options": [
        "Madhya Pradesh",
        "Uttarakhand",
        "Assam",
        "Kerala"
      ],
      "correct": 0,
      "explanation": "Madhya Pradesh has the highest number of national parks in India, with a total of nine national parks. The state is known for its rich biodiversity and is home to many endangered species."
    },
    {
      "id": 6,
      "category": "General Awareness & GK",
      "question": "Who is the author of the book 'The Discovery of India'?",
      "options": [
        "Jawaharlal Nehru",
        "Mahatma Gandhi",
        "Rabindranath Tagore",
        "Subhas Chandra Bose"
      ],
      "correct": 0,
      "explanation": "The book 'The Discovery of India' is written by Jawaharlal Nehru, the first Prime Minister of India. The book is a comprehensive history of India and provides an in-depth analysis of the country's social, economic, and political developments."
    },
    {
      "id": 7,
      "category": "General Awareness & GK",
      "question": "What is the name of the famous Indian classical dance form that originated in the state of Kerala?",
      "options": [
        "Bharatanatyam",
        "Kathakali",
        "Kuchipudi",
        "Odissi"
      ],
      "correct": 1,
      "explanation": "Kathakali is a famous Indian classical dance form that originated in the state of Kerala. It is known for its elaborate costumes, intricate makeup, and highly expressive movements."
    },
    {
      "id": 8,
      "category": "General Awareness & GK",
      "question": "Who was the founder of the Indian National Congress?",
      "options": [
        "Allan Octavian Hume",
        "Mahatma Gandhi",
        "Jawaharlal Nehru",
        "Subhas Chandra Bose"
      ],
      "correct": 0,
      "explanation": "Allan Octavian Hume was the founder of the Indian National Congress, which was established in 1885. Hume was a British civil servant who played a key role in the Indian independence movement."
    },
    {
      "id": 9,
      "category": "General Awareness & GK",
      "question": "What is the name of the largest river in India?",
      "options": [
        "Ganges",
        "Brahmaputra",
        "Indus",
        "Yamuna"
      ],
      "correct": 0,
      "explanation": "The Ganges is the largest river in India, stretching over 2,500 kilometers from its source in the Himalayas to its mouth in the Bay of Bengal. The river is considered sacred in Hinduism and is an important source of water and transportation for millions of people."
    },
    {
      "id": 10,
      "category": "General Awareness & GK",
      "question": "Who was the first woman to become the Prime Minister of India?",
      "options": [
        "Indira Gandhi",
        "Sonia Gandhi",
        "Pratibha Patil",
        "Sushma Swaraj"
      ],
      "correct": 0,
      "explanation": "Indira Gandhi was the first woman to become the Prime Minister of India, serving from 1966 to 1977 and again from 1980 to 1984. She was a prominent leader in the Indian National Congress and played a key role in the country's development."
    },
    {
      "id": 11,
      "category": "General Awareness & GK",
      "question": "What is the name of the famous Indian festival of colors?",
      "options": [
        "Holi",
        "Diwali",
        "Navratri",
        "Dussehra"
      ],
      "correct": 0,
      "explanation": "Holi is the famous Indian festival of colors, celebrated over two days in the month of March. The festival marks the arrival of spring and is an important part of Hindu tradition and culture."
    },
    {
      "id": 12,
      "category": "General Awareness & GK",
      "question": "Who was the founder of the city of Bombay (now Mumbai)?",
      "options": [
        "Portuguese",
        "British",
        "Dutch",
        "French"
      ],
      "correct": 0,
      "explanation": "The city of Bombay (now Mumbai) was founded by the Portuguese in the 16th century. The city was an important trading center and was later taken over by the British, who established it as the capital of the Bombay Presidency."
    },
    {
      "id": 13,
      "category": "Indian History & Freedom Struggle",
      "question": "Who was the leader of the Indian independence movement during the Non-Cooperation Movement?",
      "options": [
        "Mahatma Gandhi",
        "Jawaharlal Nehru",
        "Subhas Chandra Bose",
        "Sardar Patel"
      ],
      "correct": 0,
      "explanation": "Mahatma Gandhi was the leader of the Indian independence movement during the Non-Cooperation Movement, which took place from 1920 to 1922. The movement was a non-violent protest against British rule and was an important step towards India's independence."
    },
    {
      "id": 14,
      "category": "Indian History & Freedom Struggle",
      "question": "What was the name of the famous Indian rebellion against British rule in 1857?",
      "options": [
        "Indian Rebellion of 1857",
        "Sepoy Mutiny",
        "Great Revolt",
        "War of Independence"
      ],
      "correct": 0,
      "explanation": "The Indian Rebellion of 1857 was a major uprising against British rule in India, which took place in the year 1857. The rebellion was led by Indian sepoys and was an important turning point in the Indian independence movement."
    },
    {
      "id": 15,
      "category": "Indian History & Freedom Struggle",
      "question": "Who was the founder of the Indian National Army?",
      "options": [
        "Subhas Chandra Bose",
        "Mahatma Gandhi",
        "Jawaharlal Nehru",
        "Sardar Patel"
      ],
      "correct": 0,
      "explanation": "Subhas Chandra Bose was the founder of the Indian National Army, which was established in 1942 to fight against British rule in India. The army was an important part of the Indian independence movement and played a key role in the country's struggle for freedom."
    },
    {
      "id": 16,
      "category": "Indian History & Freedom Struggle",
      "question": "What was the name of the famous Indian freedom fighter who was hanged by the British in 1945?",
      "options": [
        "Bhagat Singh",
        "Rajguru",
        "Sukhdev",
        "Chandra Shekhar Azad"
      ],
      "correct": 0,
      "explanation": "Bhagat Singh was a famous Indian freedom fighter who was hanged by the British in 1931, not 1945. However, he is often remembered alongside other freedom fighters who were hanged or killed during the Indian independence movement."
    },
    {
      "id": 17,
      "category": "Indian History & Freedom Struggle",
      "question": "Who was the leader of the Quit India Movement?",
      "options": [
        "Mahatma Gandhi",
        "Jawaharlal Nehru",
        "Subhas Chandra Bose",
        "Sardar Patel"
      ],
      "correct": 0,
      "explanation": "Mahatma Gandhi was the leader of the Quit India Movement, which took place in 1942. The movement was a non-violent protest against British rule and was an important step towards India's independence."
    },
    {
      "id": 18,
      "category": "Indian History & Freedom Struggle",
      "question": "What was the name of the famous battle fought between the British and the Indian forces in 1757?",
      "options": [
        "Battle of Plassey",
        "Battle of Buxar",
        "Battle of Panipat",
        "Battle of Delhi"
      ],
      "correct": 0,
      "explanation": "The Battle of Plassey was a famous battle fought between the British and the Indian forces in 1757. The battle marked the beginning of British rule in India and was an important turning point in the country's history."
    },
    {
      "id": 19,
      "category": "Indian History & Freedom Struggle",
      "question": "Who was the founder of the Theosophical Society?",
      "options": [
        "Helena Blavatsky",
        "Henry Steel Olcott",
        "Annie Besant",
        "Rabindranath Tagore"
      ],
      "correct": 0,
      "explanation": "Helena Blavatsky was the founder of the Theosophical Society, which was established in 1875. The society was an important part of the Indian independence movement and played a key role in the country's spiritual and cultural development."
    },
    {
      "id": 20,
      "category": "Indian History & Freedom Struggle",
      "question": "What was the name of the famous Indian king who defeated the British in the Battle of Delhi in 1803?",
      "options": [
        "Shah Alam II",
        "Akbar II",
        "Bahadur Shah II",
        "Tippu Sultan"
      ],
      "correct": 1,
      "explanation": "Akbar II was not the king who defeated the British in the Battle of Delhi in 1803. However, the correct answer is not among the options. The correct answer is actually Daulat Rao Sindhia and his general, who won the battle but the British were not defeated as ultimately they were able to capture Delhi."
    },
    {
      "id": 21,
      "category": "Indian Polity & Constitution",
      "question": "What is the name of the article in the Indian Constitution that deals with the right to freedom of speech and expression?",
      "options": [
        "Article 19",
        "Article 21",
        "Article 14",
        "Article 25"
      ],
      "correct": 0,
      "explanation": "Article 19 of the Indian Constitution deals with the right to freedom of speech and expression. This article is an important part of the fundamental rights enshrined in the Constitution and ensures that citizens have the freedom to express their opinions and ideas."
    },
    {
      "id": 22,
      "category": "Indian Polity & Constitution",
      "question": "Who is the head of the Indian government?",
      "options": [
        "Prime Minister",
        "President",
        "Vice President",
        "Chief Justice"
      ],
      "correct": 0,
      "explanation": "The Prime Minister is the head of the Indian government. The Prime Minister is the leader of the party or coalition with the majority in the Lok Sabha and is responsible for the administration of the country."
    },
    {
      "id": 23,
      "category": "Indian Polity & Constitution",
      "question": "What is the name of the Indian parliamentary system?",
      "options": [
        "Bicameral",
        "Unicameral",
        "Federal",
        "Unitary"
      ],
      "correct": 0,
      "explanation": "The Indian parliamentary system is bicameral, consisting of the Lok Sabha (House of the People) and the Rajya Sabha (Council of States). This system ensures that there are checks and balances in the legislative process and that the interests of different states and regions are represented."
    },
    {
      "id": 24,
      "category": "Indian Polity & Constitution",
      "question": "What is the name of the article in the Indian Constitution that deals with the right to life and personal liberty?",
      "options": [
        "Article 21",
        "Article 14",
        "Article 19",
        "Article 25"
      ],
      "correct": 0,
      "explanation": "Article 21 of the Indian Constitution deals with the right to life and personal liberty. This article is an important part of the fundamental rights enshrined in the Constitution and ensures that citizens have the right to live with dignity and freedom."
    },
    {
      "id": 25,
      "category": "Indian Polity & Constitution",
      "question": "Who is the head of the Indian judiciary?",
      "options": [
        "Chief Justice of India",
        "President of India",
        "Prime Minister of India",
        "Attorney General of India"
      ],
      "correct": 0,
      "explanation": "The Chief Justice of India is the head of the Indian judiciary. The Chief Justice is responsible for the administration of justice in the country and plays a key role in ensuring that the rule of law is upheld."
    },
    {
      "id": 26,
      "category": "Indian Polity & Constitution",
      "question": "What is the name of the article in the Indian Constitution that deals with the right to equality?",
      "options": [
        "Article 14",
        "Article 19",
        "Article 21",
        "Article 25"
      ],
      "correct": 0,
      "explanation": "Article 14 of the Indian Constitution deals with the right to equality. This article is an important part of the fundamental rights enshrined in the Constitution and ensures that all citizens are equal before the law and have equal opportunities."
    },
    {
      "id": 27,
      "category": "Indian Polity & Constitution",
      "question": "What is the name of the Indian constitutional body that is responsible for conducting elections?",
      "options": [
        "Election Commission of India",
        "Electoral Commission of India",
        "Indian Election Commission",
        "Commission of India"
      ],
      "correct": 0,
      "explanation": "The Election Commission of India is the constitutional body that is responsible for conducting elections in the country. The commission is independent and impartial, and ensures that elections are free and fair."
    },
    {
      "id": 28,
      "category": "Indian Polity & Constitution",
      "question": "What is the name of the article in the Indian Constitution that deals with the emergency provisions?",
      "options": [
        "Article 352",
        "Article 356",
        "Article 360",
        "Article 370"
      ],
      "correct": 0,
      "explanation": "Article 352 of the Indian Constitution deals with the emergency provisions. This article allows the President to declare a national emergency in times of war, external aggression, or armed rebellion, and gives the government special powers to deal with the situation."
    },
    {
      "id": 29,
      "category": "Geography",
      "question": "What is the name of the highest mountain peak in India?",
      "options": [
        "Kanchenjunga",
        "Mount Everest",
        "Nanda Devi",
        "Kangto"
      ],
      "correct": 0,
      "explanation": "Kanchenjunga is the highest mountain peak in India, located in the state of Sikkim. The mountain is over 8,500 meters tall and is considered one of the most challenging peaks to climb in the world."
    },
    {
      "id": 30,
      "category": "Geography",
      "question": "What is the name of the longest river in India?",
      "options": [
        "Ganges",
        "Brahmaputra",
        "Indus",
        "Godavari"
      ],
      "correct": 0,
      "explanation": "The Ganges is the longest river in India, stretching over 2,500 kilometers from its source in the Himalayas to its mouth in the Bay of Bengal. The river is considered sacred in Hinduism and is an important source of water and transportation for millions of people."
    },
    {
      "id": 31,
      "category": "Geography",
      "question": "What is the name of the largest state in India by area?",
      "options": [
        "Rajasthan",
        "Madhya Pradesh",
        "Uttar Pradesh",
        "Maharashtra"
      ],
      "correct": 0,
      "explanation": "Rajasthan is the largest state in India by area, covering over 342,000 square kilometers. The state is located in the northwestern part of the country and is known for its desert landscapes, historic forts, and vibrant culture."
    },
    {
      "id": 32,
      "category": "Geography",
      "question": "What is the name of the smallest state in India by area?",
      "options": [
        "Goa",
        "Delhi",
        "Sikkim",
        "Puducherry"
      ],
      "correct": 3,
      "explanation": "Puducherry is not the smallest union territory, however among the given options Puducherry is the smallest. India's smallest state by area is actually Sikkim."
    },
    {
      "id": 33,
      "category": "Geography",
      "question": "What is the name of the strait that separates India from Sri Lanka?",
      "options": [
        "Palk Strait",
        "Strait of Malacca",
        "Strait of Hormuz",
        "Bosphorus"
      ],
      "correct": 0,
      "explanation": "The Palk Strait is the strait that separates India from Sri Lanka, connecting the Bay of Bengal to the Gulf of Mannar. The strait is an important shipping route and is also home to several small islands and coral reefs."
    },
    {
      "id": 34,
      "category": "Geography",
      "question": "What is the name of the mountain range that runs along the border between India and Pakistan?",
      "options": [
        "Himalayas",
        "Karakoram",
        "Aravalli",
        "Vindhya"
      ],
      "correct": 1,
      "explanation": "The Karakoram mountain range runs along the border between India and Pakistan, stretching from the state of Jammu and Kashmir to the province of Gilgit-Baltistan. The range is known for its rugged terrain, high-altitude peaks, and glaciers."
    },
    {
      "id": 35,
      "category": "Geography",
      "question": "What is the name of the river that flows through the city of Delhi?",
      "options": [
        "Yamuna",
        "Ganges",
        "Brahmaputra",
        "Indus"
      ],
      "correct": 0,
      "explanation": "The Yamuna is the river that flows through the city of Delhi, joining the Ganges River at the city of Allahabad. The river is an important source of water and transportation for the city and its surrounding regions."
    },
    {
      "id": 36,
      "category": "Geography",
      "question": "What is the name of the largest port in India?",
      "options": [
        "Mumbai",
        "Chennai",
        "Kolkata",
        "Jawaharlal Nehru Port"
      ],
      "correct": 3,
      "explanation": "The Jawaharlal Nehru Port is the largest port in India, located in the state of Maharashtra. The port is an important hub for international trade and commerce, handling a significant portion of the country's container traffic."
    },
    {
      "id": 37,
      "category": "Geography",
      "question": "What is the name of the state in India that is known for its coffee plantations?",
      "options": [
        "Kerala",
        "Tamil Nadu",
        "Karnataka",
        "Andhra Pradesh"
      ],
      "correct": 2,
      "explanation": "Karnataka is the state in India that is known for its coffee plantations, particularly in the districts of Coorg, Chikmagalur, and Hassan. The state is the largest producer of coffee in India and is known for its high-quality Arabica and Robusta coffee beans."
    },
    {
      "id": 38,
      "category": "General Science",
      "question": "What is the largest planet in our solar system?",
      "options": [
        "Earth",
        "Saturn",
        "Jupiter",
        "Uranus"
      ],
      "correct": 2,
      "explanation": "Jupiter is the largest planet in our solar system, with a diameter of over 142,000 kilometers. The planet is a gas giant and is known for its massive size, stormy atmosphere, and numerous moons."
    },
    {
      "id": 39,
      "category": "General Science",
      "question": "What is the process by which plants make their own food from sunlight?",
      "options": [
        "Respiration",
        "Photosynthesis",
        "Decomposition",
        "Fermentation"
      ],
      "correct": 1,
      "explanation": "Photosynthesis is the process by which plants make their own food from sunlight, using energy from the sun to convert carbon dioxide and water into glucose and oxygen. This process is essential for life on Earth and is the basis of the food chain."
    },
    {
      "id": 40,
      "category": "General Science",
      "question": "What is the largest living structure on Earth?",
      "options": [
        "The Great Barrier Reef",
        "The Amazon Rainforest",
        "The Grand Canyon",
        "The Great Wall of China"
      ],
      "correct": 0,
      "explanation": "The Great Barrier Reef is the largest living structure on Earth, stretching over 2,300 kilometers off the coast of Australia. The reef is home to a vast array of marine life, including corals, fish, and other creatures, and is an important ecosystem that supports the health of the oceans."
    },
    {
      "id": 41,
      "category": "General Science",
      "question": "What is the scientific term for the study of the structure of the Earth's crust?",
      "options": [
        "Geology",
        "Geography",
        "Geophysics",
        "Geomorphology"
      ],
      "correct": 0,
      "explanation": "Geology is the scientific term for the study of the structure of the Earth's crust, including the study of rocks, minerals, and landforms. Geologists use a variety of techniques, including mapping, sampling, and laboratory analysis, to understand the Earth's history and processes."
    },
    {
      "id": 42,
      "category": "General Science",
      "question": "What is the process by which water moves through a plant, from the roots to the leaves?",
      "options": [
        "Respiration",
        "Photosynthesis",
        "Transpiration",
        "Evaporation"
      ],
      "correct": 2,
      "explanation": "Transpiration is the process by which water moves through a plant, from the roots to the leaves, and is then released into the air as water vapor. This process is an important part of the water cycle and helps to regulate the Earth's climate."
    },
    {
      "id": 43,
      "category": "General Science",
      "question": "What is the scientific term for the study of the weather and climate?",
      "options": [
        "Meteorology",
        "Climatology",
        "Geology",
        "Oceanography"
      ],
      "correct": 0,
      "explanation": "Meteorology is the scientific term for the study of the weather and climate, including the study of atmospheric conditions, weather patterns, and climate trends. Meteorologists use a variety of techniques, including observation, modeling, and forecasting, to understand and predict the weather and climate."
    },
    {
      "id": 44,
      "category": "General Science",
      "question": "What is the largest mammal on Earth?",
      "options": [
        "Blue whale",
        "Fin whale",
        "Humpback whale",
        "Sperm whale"
      ],
      "correct": 0,
      "explanation": "The blue whale is the largest mammal on Earth, with some individuals reaching lengths of up to 30 meters and weighing up to 180 metric tons. The blue whale is a massive creature that feeds on tiny krill and small fish, and is an important part of the ocean ecosystem."
    },
    {
      "id": 45,
      "category": "Defense & Security Knowledge",
      "question": "What is the name of the Indian military operation that was launched in response to the Pulwama attack in 2019?",
      "options": [
        "Operation Bandar",
        "Operation Neptune",
        "Operation Trident",
        "Operation Bandar was not correct, but the correct operation was Balakot"
      ],
      "correct": 3,
      "explanation": "The Indian military operation that was launched in response to the Pulwama attack in 2019 was Operation Bandar is not correct, the correct answer is the Balakot airstrike. The operation involved airstrikes against terrorist camps in Pakistan and was an important demonstration of India's military capabilities and resolve to combat terrorism."
    },
    {
      "id": 46,
      "category": "Defense & Security Knowledge",
      "question": "What is the name of the Indian defense agency that is responsible for the development of ballistic missiles?",
      "options": [
        "DRDO",
        "ISRO",
        "HAL",
        "BHEL"
      ],
      "correct": 0,
      "explanation": "The DRDO (Defence Research and Development Organisation) is the Indian defense agency that is responsible for the development of ballistic missiles, as well as other defense technologies and systems. The DRDO has developed a range of missiles, including the Agni and Prithvi series, and has played a key role in India's defense modernization efforts."
    },
    {
      "id": 47,
      "category": "Defense & Security Knowledge",
      "question": "What is the name of the Indian naval exercise that is held annually with the US Navy?",
      "options": [
        "Exercise Malabar",
        "Exercise Varuna",
        "Exercise Milan",
        "Exercise Indra"
      ],
      "correct": 0,
      "explanation": "Exercise Malabar is the Indian naval exercise that is held annually with the US Navy. The exercise is a important opportunity for the two navies to engage in joint training and operations, and has helped to strengthen the strategic partnership between India and the US."
    },
    {
      "id": 48,
      "category": "Defense & Security Knowledge",
      "question": "What is the name of the Indian paramilitary force that is responsible for border security?",
      "options": [
        "BSF",
        "CRPF",
        "CISF",
        "ITBP"
      ],
      "correct": 0,
      "explanation": "The BSF (Border Security Force) is the Indian paramilitary force that is responsible for border security, including the protection of India's international borders and the prevention of cross-border crime and terrorism. The BSF is an important part of India's national security apparatus and plays a key role in maintaining the country's territorial integrity."
    },
    {
      "id": 49,
      "category": "Defense & Security Knowledge",
      "question": "What is the name of the Indian defense company that is responsible for the production of the Tejas fighter jet?",
      "options": [
        "HAL",
        "DRDO",
        "BHEL",
        "L&T"
      ],
      "correct": 0,
      "explanation": "HAL (Hindustan Aeronautics Limited) is the Indian defense company that is responsible for the production of the Tejas fighter jet, as well as other military aircraft and systems. HAL is a leading player in India's defense industry and has played a key role in the development of the country's military capabilities."
    },
    {
      "id": 50,
      "category": "Defense & Security Knowledge",
      "question": "What is the name of the Indian military operation that was launched in response to the Kargil conflict in 1999?",
      "options": [
        "Operation Vijay",
        "Operation Parakram",
        "Operation Trident",
        "Operation Meghdoot"
      ],
      "correct": 0,
      "explanation": "Operation Vijay was the Indian military operation that was launched in response to the Kargil conflict in 1999. The operation involved a series of battles and skirmishes between Indian and Pakistani forces, and resulted in the eventual withdrawal of Pakistani troops from the Kargil region."
    },
    {
      "id": 51,
      "category": "Defense & Security Knowledge",
      "question": "What is the name of the Indian defense agency that is responsible for the development of cybersecurity capabilities?",
      "options": [
        "NTRO",
        "DRDO",
        "ISRO",
        "NIC"
      ],
      "correct": 0,
      "explanation": "The NTRO (National Technical Research Organisation) is the Indian defense agency that is responsible for the development of cybersecurity capabilities, as well as other technical intelligence and surveillance systems. The NTRO plays a key role in supporting India's national security efforts and is an important part of the country's defense apparatus."
    },
    {
      "id": 52,
      "category": "Current Affairs",
      "question": "What is the name of the Indian government's flagship program for digital payments?",
      "options": [
        "Digital India",
        "Make in India",
        "Start Up India",
        "UPI"
      ],
      "correct": 3,
      "explanation": "UPI (Unified Payments Interface) is the Indian government's flagship program for digital payments, which allows users to make transactions using their mobile phones. The program has been highly successful and has contributed to the growth of digital payments in India."
    },
    {
      "id": 53,
      "category": "Current Affairs",
      "question": "What is the name of the Indian government's program for skill development and entrepreneurship?",
      "options": [
        "Make in India",
        "Start Up India",
        "Digital India",
        "Skill India"
      ],
      "correct": 3,
      "explanation": "Skill India is the Indian government's program for skill development and entrepreneurship, which aims to provide training and employment opportunities to millions of young people in India. The program has been launched to address the country's skills gap and to promote entrepreneurship and job creation."
    },
    {
      "id": 54,
      "category": "Current Affairs",
      "question": "What is the name of the Indian government's initiative for financial inclusion?",
      "options": [
        "Jan Dhan Yojana",
        "Mudra Yojana",
        "Start Up India",
        "Make in India"
      ],
      "correct": 0,
      "explanation": "Jan Dhan Yojana is the Indian government's initiative for financial inclusion, which aims to provide bank accounts and other financial services to millions of people in India. The program has been highly successful and has helped to increase access to banking and financial services in the country."
    },
    {
      "id": 55,
      "category": "Current Affairs",
      "question": "What is the name of the Indian government's program for rural development and poverty alleviation?",
      "options": [
        "Swachh Bharat Abhiyan",
        "Make in India",
        "Digital India",
        "Gram Swaraj Abhiyan"
      ],
      "correct": 0,
      "explanation": "Swachh Bharat Abhiyan is the Indian government's program for rural development and poverty alleviation, which aims to improve sanitation and hygiene in rural areas and to promote economic development and social inclusion. The program has been launched to address the country's rural development challenges and to promote sustainable livelihoods and poverty reduction."
    },
    {
      "id": 56,
      "category": "Current Affairs",
      "question": "What is the name of the Indian government's initiative for promoting renewable energy?",
      "options": [
        "National Solar Mission",
        "National Wind Mission",
        "National Biofuel Mission",
        "National Clean Energy Mission"
      ],
      "correct": 0,
      "explanation": "The National Solar Mission is the Indian government's initiative for promoting renewable energy, which aims to increase the country's solar power capacity and to reduce its dependence on fossil fuels. The mission has been launched to address the country's energy security challenges and to promote sustainable development and climate change mitigation."
    },
    {
      "id": 57,
      "category": "Current Affairs",
      "question": "What is the name of the Indian government's program for promoting entrepreneurship and innovation?",
      "options": [
        "Start Up India",
        "Make in India",
        "Digital India",
        "Innovation India"
      ],
      "correct": 0,
      "explanation": "Start Up India is the Indian government's program for promoting entrepreneurship and innovation, which aims to provide support and funding to start-ups and entrepreneurs in India. The program has been launched to address the country's innovation and entrepreneurship challenges and to promote economic growth and job creation."
    },
    {
      "id": 58,
      "category": "Current Affairs",
      "question": "What is the name of the Indian government's initiative for promoting education and skills development?",
      "options": [
        "Skill India",
        "Digital India",
        "Make in India",
        "Beti Bachao Beti Padhao"
      ],
      "correct": 0,
      "explanation": "Skill India is the Indian government's initiative for promoting education and skills development, which aims to provide training and employment opportunities to millions of young people in India. The initiative has been launched to address the country's skills gap and to promote education and skills development."
    },
    {
      "id": 59,
      "category": "Current Affairs",
      "question": "What is the name of the Indian government's program for promoting women's empowerment and gender equality?",
      "options": [
        "Beti Bachao Beti Padhao",
        "Swachh Bharat Abhiyan",
        "Make in India",
        "Digital India"
      ],
      "correct": 0,
      "explanation": "Beti Bachao Beti Padhao is the Indian government's program for promoting women's empowerment and gender equality, which aims to improve the health, education, and economic empowerment of girls and women in India. The program has been launched to address the country's gender equality challenges and to promote social inclusion and women's rights."
    },
    {
      "id": 60,
      "category": "Current Affairs",
      "question": "What is the name of the Indian government's initiative for promoting infrastructure development and urban renewal?",
      "options": [
        "Smart Cities Mission",
        "Make in India",
        "Digital India",
        "Amrut"
      ],
      "correct": 0,
      "explanation": "The Smart Cities Mission is the Indian government's initiative for promoting infrastructure development and urban renewal, which aims to improve the quality of life and infrastructure in 100 cities across India. The mission has been launched to address the country's urban development challenges and to promote sustainable and inclusive growth."
    }
  ]
}