{
  "exam": "upsc",
  "name": "UPSC Prelims",
  "date": "2026-06-27",
  "questionCount": 30,
  "questions": [
    {
      "id": 1,
      "category": "Indian History",
      "question": "Who was the founder of the Maurya Empire in India?",
      "options": [
        "Chandragupta Maurya",
        "Ashoka the Great",
        "Bindusara",
        "Harsha"
      ],
      "correct": 0,
      "explanation": "Chandragupta Maurya founded the Maurya Empire around 322 BCE, establishing one of the largest empires in Indian history."
    },
    {
      "id": 2,
      "category": "Indian History",
      "question": "During the medieval period in India, the Bhakti movement was primarily aimed at:",
      "options": [
        "Promoting Vedic rituals",
        "Reforming the Mughal administration",
        "Promoting devotional worship and social equality",
        "Advancing trade and commerce"
      ],
      "correct": 2,
      "explanation": "The Bhakti movement emphasized devotion to God and aimed at social equality, challenging caste and ritual-based distinctions."
    },
    {
      "id": 3,
      "category": "Indian History",
      "question": "Which event marked the beginning of the Civil Disobedience Movement in India's freedom struggle?",
      "options": [
        "Champaran Satyagraha",
        "Salt March",
        "Quit India Movement",
        "Non-Cooperation Movement"
      ],
      "correct": 1,
      "explanation": "The Salt March in 1930, led by Mahatma Gandhi, marked the beginning of the Civil Disobedience Movement protesting salt laws."
    },
    {
      "id": 4,
      "category": "Indian History",
      "question": "Who was the leader of the Jallianwala Bagh massacre?",
      "options": [
        "Lord Curzon",
        "General Dyer",
        "Lord Chelmsford",
        "Maulana Azad"
      ],
      "correct": 1,
      "explanation": "General Dyer ordered the massacre at Jallianwala Bagh in 1919, leading to hundreds of deaths and a turning point in Indian independence movement."
    },
    {
      "id": 5,
      "category": "Indian History",
      "question": "The First War of Indian Independence took place in which year?",
      "options": [
        "1857",
        "1919",
        "1947",
        "1824"
      ],
      "correct": 0,
      "explanation": "The First War of Indian Independence, also known as the Sepoy Mutiny, occurred in 1857."
    },
    {
      "id": 6,
      "category": "Indian Geography",
      "question": "Which river is known as the 'Ganges of the South'?",
      "options": [
        "Godavari",
        "Kaveri",
        "Krishna",
        "Tungabhadra"
      ],
      "correct": 1,
      "explanation": "The Kaveri River is often called the 'Ganges of the South' because of its religious and cultural significance."
    },
    {
      "id": 7,
      "category": "Indian Geography",
      "question": "Which is the largest island in India?",
      "options": [
        "Andaman Islands",
        "Nicobar Islands",
        "Sri Lanka",
        "Lakshadweep"
      ],
      "correct": 0,
      "explanation": "The Andaman Islands are the largest group of islands owned by India, with South Andaman being the largest among them."
    },
    {
      "id": 8,
      "category": "Indian Geography",
      "question": "Which climatic zone covers most of Rajasthan?",
      "options": [
        "Tropical humid",
        "Arid desert",
        "Subtropical humid",
        "Mountains"
      ],
      "correct": 1,
      "explanation": "Most of Rajasthan falls under the Arid desert climatic zone, characterized by low rainfall and high temperatures."
    },
    {
      "id": 9,
      "category": "Indian Geography",
      "question": "Which resource is predominantly found in the Deccan Plateau?",
      "options": [
        "Coal",
        "Bauxite",
        "Gold",
        "Iron ore"
      ],
      "correct": 2,
      "explanation": "Gold deposits are notably found in the Deccan Plateau region, especially in regions like Karnataka."
    },
    {
      "id": 10,
      "category": "Indian Polity & Governance",
      "question": "Who appoints the Chief Justice of India?",
      "options": [
        "President of India",
        "Prime Minister of India",
        "Lok Sabha",
        "Supreme Court Collegium"
      ],
      "correct": 0,
      "explanation": "The President of India appoints the Chief Justice of India, typically based on seniority and recommendations of the collegium."
    },
    {
      "id": 11,
      "category": "Indian Polity & Governance",
      "question": "The Parliament of India is a:",
      "options": [
        "Unicameral legislature",
        "Bicameral legislature",
        "Tricameral legislature",
        "Multicameral legislature"
      ],
      "correct": 1,
      "explanation": "India has a bicameral parliament consisting of the Lok Sabha (House of the People) and the Rajya Sabha (Council of States)."
    },
    {
      "id": 12,
      "category": "Indian Polity & Governance",
      "question": "Which article of the Indian Constitution deals with the Fundamental Rights?",
      "options": [
        "Article 14",
        "Articles 12-35",
        "Article 21",
        "Article 370"
      ],
      "correct": 1,
      "explanation": "Articles 12 to 35 of the Indian Constitution deal comprehensively with Fundamental Rights."
    },
    {
      "id": 13,
      "category": "Indian Polity & Governance",
      "question": "The Panchayati Raj system in India is based on the principles of:",
      "options": [
        "Centralization",
        "Decentralization and Democratic autonomy",
        "Monarchical rule",
        "Federalism with unitary dominance"
      ],
      "correct": 1,
      "explanation": "Panchayati Raj emphasizes decentralization and local self-governance, promoting democratic autonomy at the village level."
    },
    {
      "id": 14,
      "category": "Indian Polity & Governance",
      "question": "Which body interprets the Constitution of India?",
      "options": [
        "Lok Sabha",
        "Supreme Court",
        "President",
        "Union Cabinet"
      ],
      "correct": 1,
      "explanation": "The Supreme Court of India is the highest judicial authority for interpreting the Constitution."
    },
    {
      "id": 15,
      "category": "Indian Economy",
      "question": "India’s GDP is primarily generated from which sector?",
      "options": [
        "Agriculture",
        "Manufacturing",
        "Services",
        "Mining"
      ],
      "correct": 2,
      "explanation": "The Services sector contributes the largest share to India’s GDP, followed by Industry and Agriculture."
    },
    {
      "id": 16,
      "category": "Indian Economy",
      "question": "The Union Budget of India is presented by the:",
      "options": [
        "Prime Minister",
        "Finance Minister",
        "President",
        "Lok Sabha Speaker"
      ],
      "correct": 1,
      "explanation": "The Finance Minister presents the Union Budget of India before Parliament."
    },
    {
      "id": 17,
      "category": "Indian Economy",
      "question": "Which financial institution is responsible for providing loans to the agricultural sector in India?",
      "options": [
        "RBI",
        "NABARD",
        "SIDBI",
        "ICICI Bank"
      ],
      "correct": 1,
      "explanation": "NABARD (National Bank for Agriculture and Rural Development) is responsible for providing financial support to agriculture."
    },
    {
      "id": 18,
      "category": "Indian Economy",
      "question": "Which five-year plan focused on replacing imports with domestic production?",
      "options": [
        "First Five Year Plan",
        "Second Five Year Plan",
        "Third Five Year Plan",
        "Fifth Five Year Plan"
      ],
      "correct": 1,
      "explanation": "The Second Five Year Plan (1956-1961) emphasized self-sufficiency and replacing imports with domestic production."
    },
    {
      "id": 19,
      "category": "General Science",
      "question": "What is the primary function of chlorophyll in plants?",
      "options": [
        "Absorbing water",
        "Photosynthesis",
        "Transportation of nutrients",
        "Reproduction"
      ],
      "correct": 1,
      "explanation": "Chlorophyll is essential for photosynthesis, allowing plants to convert light into chemical energy."
    },
    {
      "id": 20,
      "category": "General Science",
      "question": "Which element is most abundant in the Earth’s crust?",
      "options": [
        "Oxygen",
        "Silicon",
        "Aluminum",
        "Iron"
      ],
      "correct": 0,
      "explanation": "Oxygen is the most abundant element in the Earth's crust, primarily in the form of silicate minerals."
    },
    {
      "id": 21,
      "category": "General Science",
      "question": "Which part of the human body produces insulin?",
      "options": [
        "Liver",
        "Kidneys",
        "Pancreas",
        "Stomach"
      ],
      "correct": 2,
      "explanation": "The pancreas produces insulin, which regulates blood sugar levels."
    },
    {
      "id": 22,
      "category": "General Science",
      "question": "The rocket technology primarily depends on which physical principle?",
      "options": [
        "Archimedes' principle",
        "Newton's third law",
        "Bernoulli's principle",
        "Pascal's law"
      ],
      "correct": 1,
      "explanation": "Rocket propulsion is based on Newton's third law: for every action, there is an equal and opposite reaction."
    },
    {
      "id": 23,
      "category": "Environment & Ecology",
      "question": "Which is the largest biodiversity hotspot in India?",
      "options": [
        "Western Ghats",
        "Himalayas",
        "Indo-Burma",
        "Sundaland"
      ],
      "correct": 0,
      "explanation": "The Western Ghats is the largest biodiversity hotspot in India, rich in endemic species."
    },
    {
      "id": 24,
      "category": "Environment & Ecology",
      "question": "The Convention on Biological Diversity (CBD) was adopted in which year?",
      "options": [
        "1992",
        "2000",
        "1980",
        "2010"
      ],
      "correct": 0,
      "explanation": "The CBD was adopted in 1992 during the Earth Summit in Rio de Janeiro."
    },
    {
      "id": 25,
      "category": "Environment & Ecology",
      "question": "Which protected area is India’s first UNESCO World Heritage Site for natural reasons?",
      "options": [
        "Kaziranga National Park",
        "Sundarbans National Park",
        "Gir Forest",
        "Nanda Devi National Park"
      ],
      "correct": 0,
      "explanation": "Kaziranga National Park was designated as a UNESCO World Heritage Site for its unique biodiversity and natural significance."
    },
    {
      "id": 26,
      "category": "Environment & Ecology",
      "question": "The Forest Conservation Act, 1980, aims to:",
      "options": [
        "Promote afforestation",
        "Reduce deforestation by regulating and restricting the de-reservation of forests",
        "Protect wildlife species",
        "Control pollution"
      ],
      "correct": 1,
      "explanation": "The Act aims to regulate deforestation by requiring prior approval for de-reservation or use of forest land for non-forest purposes."
    },
    {
      "id": 27,
      "category": "Current Affairs & GK",
      "question": "Who is the current President of India as of 2026?",
      "options": [
        "Droupadi Murmu",
        "Ram Nath Kovind",
        "Pranab Mukherjee",
        "Shankar Dayal Sharma"
      ],
      "correct": 0,
      "explanation": "Droupadi Murmu has been serving as the President of India since 25 July 2022."
    },
    {
      "id": 28,
      "category": "Current Affairs & GK",
      "question": "Mohan Charan Majhi assumed the office of Chief Minister of Odisha on:",
      "options": [
        "12 June 2024",
        "15 August 2023",
        "1 July 2025",
        "26 January 2024"
      ],
      "correct": 0,
      "explanation": "Mohan Charan Majhi became the Chief Minister of Odisha on 12 June 2024."
    },
    {
      "id": 29,
      "category": "Current Affairs & GK",
      "question": "Who is the current External Affairs Minister of India as of 2026?",
      "options": [
        "S. Jaishankar",
        "Nirmala Sitharaman",
        "Rajnath Singh",
        "Amit Shah"
      ],
      "correct": 0,
      "explanation": "S. Jaishankar has been the External Affairs Minister since 2019, handling India's foreign relations."
    },
    {
      "id": 30,
      "category": "Current Affairs & GK",
      "question": "Which major international sports event took place in India recently?",
      "options": [
        "2018 FIFA World Cup",
        "2023 Cricket World Cup",
        "2024 Asian Games",
        "2025 Commonwealth Games"
      ],
      "correct": 2,
      "explanation": "The 2023 Asian Games were hosted in India, marking a significant international sports event."
    }
  ]
}