{
  "exam": "upsc",
  "name": "UPSC Prelims",
  "date": "2026-05-07",
  "questionCount": 30,
  "questions": [
    {
      "id": 1,
      "category": "Indian History",
      "question": "Which ancient Indian university was known for its teachings in Buddhism and attracted students from across Asia?",
      "options": [
        "Nalanda University",
        "Takshashila University",
        "Valabhi University",
        "Kashi University"
      ],
      "correct": 0,
      "explanation": "Nalanda University was an ancient center of learning in India, renowned for Buddhist studies and attracting students from various countries."
    },
    {
      "id": 2,
      "category": "Indian History",
      "question": "Who was the leader of the Non-Cooperation Movement launched in 1920?",
      "options": [
        "Mahatma Gandhi",
        "Jawaharlal Nehru",
        "Subhas Chandra Bose",
        "Bal Gangadhar Tilak"
      ],
      "correct": 0,
      "explanation": "Mahatma Gandhi led the Non-Cooperation Movement against British rule in 1920, promoting non-violent resistance."
    },
    {
      "id": 3,
      "category": "Indian History",
      "question": "The Partition of Bengal in 1905 was reversed in which year?",
      "options": [
        "1911",
        "1915",
        "1920",
        "1935"
      ],
      "correct": 0,
      "explanation": "The Partition of Bengal was annulled in 1911 due to widespread protests and opposition."
    },
    {
      "id": 4,
      "category": "Indian History",
      "question": "Which treaty marked the end of the First War of Indian Independence in 1857?",
      "options": [
        "Treaty of Allahabad",
        "Treaty of Seringapatam",
        "Treaty of Indian Independence",
        "There was no treaty; it was a rebellion"
      ],
      "correct": 3,
      "explanation": "The 1857 rebellion was a widespread uprising; it was not a formal treaty but was suppressed without a treaty signing."
    },
    {
      "id": 5,
      "category": "Indian History",
      "question": "Who was the first President of India?",
      "options": [
        "Dr. Rajendra Prasad",
        "Dr. B.R. Ambedkar",
        "Jawaharlal Nehru",
        "Rajendra Prasad"
      ],
      "correct": 0,
      "explanation": "Dr. Rajendra Prasad was the first President of India, serving from 1950 to 1962."
    },
    {
      "id": 6,
      "category": "Indian Geography",
      "question": "Which river is known as the 'Sorrow of Bihar'?",
      "options": [
        "Ganga",
        "Koshi",
        "Son",
        "Ghaghara"
      ],
      "correct": 1,
      "explanation": "Koshi River is called the 'Sorrow of Bihar' due to frequent flooding."
    },
    {
      "id": 7,
      "category": "Indian Geography",
      "question": "Which is the largest island in India?",
      "options": [
        "Andaman Islands",
        "Lakshadweep",
        "Minicoy",
        "Nicobar Islands"
      ],
      "correct": 0,
      "explanation": "Andaman Islands are the largest group of islands in India geographically."
    },
    {
      "id": 8,
      "category": "Indian Geography",
      "question": "The Thar Desert is primarily located in which Indian state?",
      "options": [
        "Rajasthan",
        "Gujarat",
        "Punjab",
        "Haryana"
      ],
      "correct": 0,
      "explanation": "The Thar Desert mainly spans Rajasthan, with parts in Gujarat, Punjab, and Haryana."
    },
    {
      "id": 9,
      "category": "Indian Geography",
      "question": "Which resource is India's largest domestic source of energy?",
      "options": [
        "Coal",
        "Hydropower",
        "Natural Gas",
        "Renewable Energy"
      ],
      "correct": 0,
      "explanation": "Coal is the largest domestic energy resource in India, forming the backbone of power generation."
    },
    {
      "id": 10,
      "category": "Indian Polity & Governance",
      "question": "Who appoints the Chief Justice of India?",
      "options": [
        "President of India",
        "Prime Minister of India",
        "Lok Sabha",
        "Supreme Court Collegium"
      ],
      "correct": 0,
      "explanation": "The President of India appoints the Chief Justice of India based on the recommendation of the Collegium."
    },
    {
      "id": 11,
      "category": "Indian Polity & Governance",
      "question": "Which article of the Indian Constitution deals with Fundamental Rights?",
      "options": [
        "Article 12",
        "Articles 14-32",
        "Articles 368-371",
        "Article 51"
      ],
      "correct": 1,
      "explanation": "Articles 14 to 32 of the Indian Constitution enumerate the Fundamental Rights."
    },
    {
      "id": 12,
      "category": "Indian Polity & Governance",
      "question": "The Lok Sabha has a term of how many years?",
      "options": [
        "3 years",
        "4 years",
        "5 years",
        "6 years"
      ],
      "correct": 2,
      "explanation": "The Lok Sabha's term is five years unless dissolved earlier."
    },
    {
      "id": 13,
      "category": "Indian Polity & Governance",
      "question": "Which body is considered the guardian of the Indian Constitution?",
      "options": [
        "Parliament",
        "Supreme Court",
        "President",
        "Lok Sabha"
      ],
      "correct": 1,
      "explanation": "The Supreme Court is the guardian and interpreter of the Constitution."
    },
    {
      "id": 14,
      "category": "Indian Polity & Governance",
      "question": "Which fundamental Right guarantees the Right to Equality?",
      "options": [
        "Article 14",
        "Article 19",
        "Article 21",
        "Article 32"
      ],
      "correct": 0,
      "explanation": "Article 14 guarantees equality before law and equal protection of laws."
    },
    {
      "id": 15,
      "category": "Indian Economy",
      "question": "The Union Budget of India is presented in which house of Parliament?",
      "options": [
        "Lok Sabha",
        "Rajya Sabha",
        "President's House",
        "Ministry of Finance"
      ],
      "correct": 0,
      "explanation": "The Budget is presented in the Lok Sabha, the lower house of Parliament."
    },
    {
      "id": 16,
      "category": "Indian Economy",
      "question": "What does GDP stand for?",
      "options": [
        "Gross Domestic Product",
        "Gross Development Plan",
        "General Development Policy",
        "Global Domestic Price"
      ],
      "correct": 0,
      "explanation": "GDP stands for Gross Domestic Product, representing the total value of goods and services produced."
    },
    {
      "id": 17,
      "category": "Indian Economy",
      "question": "Which five-year plan focused on self-reliance and import substitution?",
      "options": [
        "First Plan",
        "Second Plan",
        "Third Plan",
        "Fifth Plan"
      ],
      "correct": 2,
      "explanation": "The Third Plan (1961-1966) emphasized self-reliance and import substitution strategies."
    },
    {
      "id": 18,
      "category": "Indian Economy",
      "question": "Which institution is responsible for Monetary Policy in India?",
      "options": [
        "RBI (Reserve Bank of India)",
        "Finance Ministry",
        "SEBI",
        "Planning Commission"
      ],
      "correct": 0,
      "explanation": "The Reserve Bank of India (RBI) formulates and implements monetary policy."
    },
    {
      "id": 19,
      "category": "General Science",
      "question": "Which scientist is known as the 'Father of Modern Physics'?",
      "options": [
        "Albert Einstein",
        "Isaac Newton",
        "Galileo Galilei",
        "Niels Bohr"
      ],
      "correct": 0,
      "explanation": "Albert Einstein is regarded as the father of modern physics for his theory of relativity."
    },
    {
      "id": 20,
      "category": "General Science",
      "question": "Which element has the highest electronegativity?",
      "options": [
        "Oxygen",
        "Fluorine",
        "Chlorine",
        "Nitrogen"
      ],
      "correct": 1,
      "explanation": "Fluorine has the highest electronegativity among elements."
    },
    {
      "id": 21,
      "category": "General Science",
      "question": "Which part of the human body is primarily affected by Alzheimer’s disease?",
      "options": [
        "Heart",
        "Liver",
        "Brain",
        "Kidneys"
      ],
      "correct": 2,
      "explanation": "Alzheimer's disease affects the brain, leading to memory loss and cognitive decline."
    },
    {
      "id": 22,
      "category": "General Science",
      "question": "The Hubble Space Telescope orbits the Earth at an altitude of approximately:",
      "options": [
        "540 km",
        "600 km",
        "547 km",
        "1000 km"
      ],
      "correct": 2,
      "explanation": "The Hubble Space Telescope orbits roughly 547 km above Earth."
    },
    {
      "id": 23,
      "category": "Environment & Ecology",
      "question": "The Convention on Biological Diversity (CBD) was adopted in which year?",
      "options": [
        "1992",
        "2000",
        "1982",
        "2010"
      ],
      "correct": 0,
      "explanation": "CBD was adopted in 1992 during the Earth Summit in Rio de Janeiro."
    },
    {
      "id": 24,
      "category": "Environment & Ecology",
      "question": "Which of the following is a critically endangered species in India?",
      "options": [
        "Indian Elephant",
        "Ganges River Dolphin",
        "Bengal Tiger",
        "Indian Rhinoceros"
      ],
      "correct": 1,
      "explanation": "The Ganges River Dolphin is critically endangered due to habitat loss and pollution."
    },
    {
      "id": 25,
      "category": "Environment & Ecology",
      "question": "Which protected area is known for its population of tigers in India?",
      "options": [
        "Sundarbans National Park",
        "Kaziranga National Park",
        "Bandipur National Park",
        "Jim Corbett National Park"
      ],
      "correct": 3,
      "explanation": "Jim Corbett National Park was the first National Park in India and is famous for tiger conservation."
    },
    {
      "id": 26,
      "category": "Environment & Ecology",
      "question": "The Kyoto Protocol is related to which global environmental issue?",
      "options": [
        "Deforestation",
        "Climate Change",
        "Ozone Depletion",
        "Water Pollution"
      ],
      "correct": 1,
      "explanation": "The Kyoto Protocol is an international treaty that commits state parties to reduce greenhouse gas emissions."
    },
    {
      "id": 27,
      "category": "Current Affairs & GK",
      "question": "Who is the current President of India as of 2026?",
      "options": [
        "Droupadi Murmu",
        "Pranab Mukherjee",
        "Ram Nath Kovind",
        "V.V. Giri"
      ],
      "correct": 0,
      "explanation": "Droupadi Murmu is the current President of India since 2022."
    },
    {
      "id": 28,
      "category": "Current Affairs & GK",
      "question": "Who is the current Chief Minister of Odisha?",
      "options": [
        "Naveen Patnaik",
        "Mohan Charan Majhi",
        "Shahbaz Sharif",
        "Uddhav Thackeray"
      ],
      "correct": 1,
      "explanation": "Mohan Charan Majhi is the current Chief Minister of Odisha since 12 June 2024."
    },
    {
      "id": 29,
      "category": "Current Affairs & GK",
      "question": "Which international organization awarded the Nobel Peace Prize in 2023?",
      "options": [
        "World Food Programme",
        "UNHCR",
        "International Committee of the Red Cross",
        "UNDP"
      ],
      "correct": 0,
      "explanation": "The World Food Programme received the Nobel Peace Prize in 2023 for its efforts to combat hunger."
    },
    {
      "id": 30,
      "category": "Current Affairs & GK",
      "question": "Who is the current External Affairs Minister of India?",
      "options": [
        "S. Jaishankar",
        "Subrahmanyam Jaishankar",
        "Rajnath Singh",
        "Nirmala Sitharaman"
      ],
      "correct": 0,
      "explanation": "S. Jaishankar has been serving as the External Affairs Minister of India since 2019."
    }
  ]
}